Workbook

Sheet Assumptions
B2: CARPAL.KG — Unit Economics
B3: Все синие ячейки — входные данные, меняй их. Чёрное — формулы. Цены: рынок Бишкека, июнь 2026 (см. источники справа).
B5: БАЗОВЫЕ ДОПУЩЕНИЯ | C5: Значение | D5: Ед. | E5: Источник / комментарий
B6: Курс USD/KGS | C6: 87.5 | D6: KGS | E6: ЦБ КР, июнь 2026 (ориентир)
B7: Суточная ставка K5 — рынок (Лалафо/прокат) | C7: 5000 | D7: KGS | E7: Лалафо ~1400-5000с; Nomad Kia от $70. K5=бизнес-класс
B8: Суточная ставка K5 — на Carpal (премия за доверие) | C8: 5500 | D8: KGS | E8: +10% за проверенную сделку, депозит в банке, поддержку
B9: Загрузка авто на Лалафо (дней/мес) | C9: 8 | D9: дней | E9: Самостоятельная сдача: низкая загрузка, простои, торг
B10: Загрузка авто на Carpal (дней/мес) | C10: 13 | D10: дней | E10: Поток туристов + календарь + видимость => выше utilization
B11: Средняя длительность аренды | C11: 3 | D11: дней | E11: Туристический трип Бишкек/Иссык-Куль
B12: Комиссия Carpal с владельца | C12: 0.18 | D12: % | E12: Базовый сценарий (см. лист Commission_Scenarios)
B13: Сервисный сбор с арендатора | C13: 0 | D13: % | E13: 0 в базовом; вариант на листе сценариев
B14: Расход владельца на сделку (мойка, топливо-овэрхед) | C14: 300 | D14: KGS | E14: Оценка на 1 аренду
B15: Размер депозита (блокировка в банке) | C15: 30000 | D15: KGS | E15: Не доход; иллюстрация класса авто

Sheet Owner_KIA_K5
B2: Сколько заработает владелец KIA K5: Лалафо vs Carpal (в месяц)
B3: Главный аргумент: Carpal не отнимает комиссией — поднимает загрузку и цену. Комиссия берётся из прироста.
B5: Показатель (в месяц на 1 авто) | C5: Лалафо (сам) | D5: Carpal | E5: Δ
B6: Суточная ставка, KGS | C6: =Assumptions!C7 -> 5000 | D6: =Assumptions!C8 -> 5500 | E6: =D6-C6 -> 500
B7: Загрузка, дней/мес | C7: =Assumptions!C9 -> 8 | D7: =Assumptions!C10 -> 13 | E7: =D7-C7 -> 5
B8: Валовая выручка от аренды, KGS | C8: =C6*C7 -> 40000 | D8: =D6*D7 -> 71500 | E8: =D8-C8 -> 31500
B9: Комиссия Carpal с владельца | C9: =0 -> 0 | D9: =D8*Assumptions!C12 -> 12870 | E9: =D9-C9 -> 12870
B10: Расходы владельца на сделки, KGS | C10: =(C7/Assumptions!C11)*Assumptions!C14 -> 800 | D10: =(D7/Assumptions!C11)*Assumptions!C14 -> 1300 | E10: =D10-C10 -> 500
B11: ЧИСТЫЙ доход владельца, KGS | C11: =C8-C9-C10 -> 39200 | D11: =D8-D9-D10 -> 57330 | E11: =D11-C11 -> 18130
B12: Чистый доход владельца, USD | C12: =C11/Assumptions!C6 -> 448 | D12: =D11/Assumptions!C6 -> 655.2 | E12: =D12-C12 -> 207.2
B14: Прирост дохода владельца на Carpal, % | D14: =D11/C11-1 -> 0.4625
B16: ВЫВОД ДЛЯ ВЛАДЕЛЬЦА
B17: ="Даже отдавая " & TEXT(Assumptions!C12,"0%") & " комиссии, владелец зарабатывает на " & TEXT(D14,"0%") & " БОЛЬШЕ, чем на Лалафо — за счёт загрузки и цены." -> Даже отдавая 18% комиссии, владелец зарабатывает на 46% БОЛЬШЕ, чем на Лалафо — за счёт загрузки и цены.

Sheet Commission_Scenarios
B2: Три модели комиссии — что берёт Carpal с одной аренды (3 дня, K5)
B3: Считаем доход платформы (доход платформы) на сделку. Синее — ставки, крути их.
B5: Параметр | C5: A: 18% с владельца | D5: B: split 10%+8% | E5: C: 8% влад + 12% арендатор
B6: Стоимость аренды (3 дня), KGS | C6: =Assumptions!C8*Assumptions!C11 -> 16500 | D6: =Assumptions!C8*Assumptions!C11 -> 16500 | E6: =Assumptions!C8*Assumptions!C11 -> 16500
B7: Комиссия с владельца, % | C7: 0.18 | D7: 0.1 | E7: 0.08
B8: Сервисный сбор с арендатора, % | C8: 0 | D8: 0.08 | E8: 0.12
B9: ДОХОД CARPAL с 1 аренды (доход платформы), KGS | C9: =C6*C7+C6*C8 -> 2970 | D9: =D6*D7+D6*D8 -> 2970 | E9: =E6*E7+E6*E8 -> 3300
B10: Доход Carpal с 1 аренды, USD | C10: =C9/Assumptions!C6 -> 33.942857 | D10: =D9/Assumptions!C6 -> 33.942857 | E10: =E9/Assumptions!C6 -> 37.714286
B13: МАСШТАБ: доход платформы при росте числа аренд (берёт сценарий A)
B14: Этап | C14: Аренд/мес | D14: Доход Carpal/мес, USD | E14: Накопл. GMV/мес, USD
B15: Месяц 1 (beta) | C15: 10 | D15: =C15*$C$10 -> 339.42857 | E15: =C15*$C$6/Assumptions!C6 -> 1885.7143
B16: Месяц 3 (цель tranche2) | C16: 30 | D16: =C16*$C$10 -> 1018.2857 | E16: =C16*$C$6/Assumptions!C6 -> 5657.1429
B17: Месяц 6 | C17: 80 | D17: =C17*$C$10 -> 2715.4286 | E17: =C17*$C$6/Assumptions!C6 -> 15085.714
B18: Месяц 12 (цель) | C18: 250 | D18: =C18*$C$10 -> 8485.7143 | E18: =C18*$C$6/Assumptions!C6 -> 47142.857
B21: РЕКОМЕНДАЦИЯ ПО КОМИССИИ
B22: Сценарий B (split 10% владелец + 8% арендатор) — психологически мягче для обеих сторон: владелец видит «всего 10%», арендатор платит сервисный сбор за гарантию (как Booking/Airbnb). Суммарный доход платформы тот же ~18%, но оба чувствуют справедливость. На старте — 0% владельцу для набора supply, сбор с арендатора оставить (турист платит за доверие охотно).

Sheet CapTable_Mervey
B2: Доля Mervey (35% капитала) — возврат с прибыли
B3: 35% — доля в КАПИТАЛЕ, не в выручке. Возврат считается с прибыли. Синее — входные ставки.
B5: ВХОДНЫЕ ДАННЫЕ
B6: Доход платформы, мес.12 годовой темп, USD/год | C6: 101832
B7: Доля Mervey в капитале | C7: 0.35
B9: СЦЕНАРИИ ОПЕРАЦИОННОЙ МАРЖИ
B10: Сценарий | C10: Маржа | D10: Прибыль/год | E10: Доля Mervey/год
B11: Консервативный (ранняя стадия) | C11: 0.2 | D11: =$C$6*C11 -> 20366.4 | E11: =D11*$C$7 -> 7128.24
B12: Базовый (зрелый marketplace) | C12: 0.35 | D12: =$C$6*C12 -> 35641.2 | E12: =D12*$C$7 -> 12474.42
B13: Оптимистичный (автоматизация) | C13: 0.5 | D13: =$C$6*C13 -> 50916 | E13: =D13*$C$7 -> 17820.6
B16: ПРИМЕЧАНИЕ
B17: Это годовой денежный поток на доле, не разовая выплата. Главная стоимость доли Mervey — 35% капитала растущей компании: при раунде или выходе стоимость доли кратно превышает годовой возврат. На стадии первого транша прибыль реинвестируется в рост — дивидендов нет по плану.
